{
  "authorDailyContributionsMap": {
    "itssodium": [
      {
        "date": "2020-08-16",
        "commitResults": [
          {
            "hash": "1d1076d06e689e6d2409d4fd025783e0dfbb8efa",
            "messageTitle": "Level 1",
            "messageBody": "",
            "fileTypesAndContributionMap": {
              "txt": {
                "insertions": 3,
                "deletions": 0
              },
              "java": {
                "insertions": 43,
                "deletions": 2
              }
            }
          },
          {
            "hash": "e6435a953677c7e56929fd9cbc6edfd425dd3805",
            "messageTitle": "Level 1",
            "messageBody": "",
            "fileTypesAndContributionMap": {
              "java": {
                "insertions": 10,
                "deletions": 8
              }
            }
          },
          {
            "hash": "55f3edf3745e3c24a9130f120bff59afc0341814",
            "messageTitle": "Level 2",
            "messageBody": "",
            "fileTypesAndContributionMap": {
              "txt": {
                "insertions": 2,
                "deletions": 1
              },
              "java": {
                "insertions": 10,
                "deletions": 3
              }
            }
          },
          {
            "hash": "a44740bed2af481ecaa1082b26f35177a5ba2b9e",
            "messageTitle": "Level 3",
            "messageBody": "",
            "fileTypesAndContributionMap": {
              "txt": {
                "insertions": 1,
                "deletions": 0
              },
              "java": {
                "insertions": 93,
                "deletions": 5
              }
            }
          },
          {
            "hash": "869c2f61be1c5a961f37ee9a700914526dcba479",
            "messageTitle": "Level-3",
            "messageBody": "",
            "fileTypesAndContributionMap": {
              "java": {
                "insertions": 1,
                "deletions": 1
              }
            }
          },
          {
            "hash": "168707b58321d090dd8843df46008322e4fde688",
            "messageTitle": "Level-4",
            "messageBody": "",
            "fileTypesAndContributionMap": {
              "txt": {
                "insertions": 4,
                "deletions": 4
              },
              "java": {
                "insertions": 66,
                "deletions": 4
              }
            }
          },
          {
            "hash": "1ccbe557e29cdef080b36bc3efa2bd0cc5713d4a",
            "messageTitle": "Level-4",
            "messageBody": "",
            "fileTypesAndContributionMap": {
              "java": {
                "insertions": 5,
                "deletions": 5
              }
            }
          }
        ]
      },
      {
        "date": "2020-08-17",
        "commitResults": [
          {
            "hash": "e19fa4218f87f2d3330abf24b1d32de397a91f8a",
            "messageTitle": "A-TextUiTesting",
            "messageBody": "",
            "fileTypesAndContributionMap": {
              "txt": {
                "insertions": 6,
                "deletions": 3
              },
              "java": {
                "insertions": 24,
                "deletions": 60
              },
              "sh": {
                "insertions": 6,
                "deletions": 6
              }
            }
          },
          {
            "hash": "cb7399437a1587cbf41bd6559540a62769abfb5d",
            "messageTitle": "Level-5",
            "messageBody": "",
            "fileTypesAndContributionMap": {
              "java": {
                "insertions": 60,
                "deletions": 43
              }
            }
          }
        ]
      },
      {
        "date": "2020-08-18",
        "commitResults": [
          {
            "hash": "cc985f4f624854e305f42ffc9a63943992353f1a",
            "messageTitle": "A-TextUiTesting",
            "messageBody": "",
            "fileTypesAndContributionMap": {
              "txt": {
                "insertions": 2,
                "deletions": 4
              },
              "java": {
                "insertions": 32,
                "deletions": 35
              },
              "sh": {
                "insertions": 1,
                "deletions": 0
              }
            }
          },
          {
            "hash": "fc66ec6817a44371a3b7f45b3d6fe026c792c331",
            "messageTitle": "Level-5",
            "messageBody": "",
            "fileTypesAndContributionMap": {
              "txt": {
                "insertions": 3,
                "deletions": 6
              },
              "java": {
                "insertions": 23,
                "deletions": 29
              }
            }
          }
        ]
      },
      {
        "date": "2020-08-19",
        "commitResults": [
          {
            "hash": "589fa2b041d1e23cce03524a8fd89779008898ba",
            "messageTitle": "Level-5",
            "messageBody": "",
            "fileTypesAndContributionMap": {
              "java": {
                "insertions": 77,
                "deletions": 3
              }
            }
          },
          {
            "hash": "508f418522eb7a769777505ee1060b32506ca748",
            "messageTitle": "Level-5",
            "messageBody": "",
            "fileTypesAndContributionMap": {
              "txt": {
                "insertions": 5,
                "deletions": 0
              },
              "java": {
                "insertions": 6,
                "deletions": 6
              }
            }
          },
          {
            "hash": "6870b39ae70403a1de61e4665f78f017b8eee896",
            "messageTitle": "Level-5",
            "messageBody": "",
            "fileTypesAndContributionMap": {
              "txt": {
                "insertions": 1,
                "deletions": 7
              },
              "java": {
                "insertions": 11,
                "deletions": 14
              }
            }
          }
        ]
      },
      {
        "date": "2020-08-20",
        "commitResults": [
          {
            "hash": "45da9cd5e2fbde4d75c3dad1b279c35a005427ad",
            "messageTitle": "Level-5",
            "messageBody": "",
            "fileTypesAndContributionMap": {
              "java": {
                "insertions": 1,
                "deletions": 0
              }
            }
          },
          {
            "hash": "150fd721a80a46a96ff3908a959ac1d2606d9bad",
            "messageTitle": "Level-6",
            "messageBody": "",
            "fileTypesAndContributionMap": {
              "txt": {
                "insertions": 10,
                "deletions": 2
              },
              "java": {
                "insertions": 297,
                "deletions": 42
              }
            }
          },
          {
            "hash": "983fe3169b77ae18e2cb365d8bfc40a1c705f353",
            "messageTitle": "Level-6",
            "messageBody": "",
            "fileTypesAndContributionMap": {
              "txt": {
                "insertions": 2,
                "deletions": 2
              }
            }
          },
          {
            "hash": "b7bb5d5cf0b8f92c956d0a4e3e0c723201501831",
            "messageTitle": "Level-6",
            "messageBody": "",
            "fileTypesAndContributionMap": {
              "txt": {
                "insertions": 11,
                "deletions": 0
              }
            }
          },
          {
            "hash": "ddd57f2b55ddeed7eaaa284b699635bc47fa08b5",
            "messageTitle": "Level-6",
            "messageBody": "",
            "fileTypesAndContributionMap": {
              "java": {
                "insertions": 1,
                "deletions": 0
              }
            }
          },
          {
            "hash": "614496b49b15e630eb298bab760cc9490ffa30a4",
            "messageTitle": "Level-1",
            "messageBody": "",
            "tags": [
              "Level-1"
            ],
            "fileTypesAndContributionMap": {
              "txt": {
                "insertions": 2,
                "deletions": 19
              },
              "java": {
                "insertions": 15,
                "deletions": 494
              }
            }
          },
          {
            "hash": "0f9829f5f010656699ca2ece8c486de3b3407134",
            "messageTitle": "Level-2",
            "messageBody": "",
            "tags": [
              "Level-2"
            ],
            "fileTypesAndContributionMap": {
              "txt": {
                "insertions": 2,
                "deletions": 1
              },
              "java": {
                "insertions": 20,
                "deletions": 7
              }
            }
          },
          {
            "hash": "eecbe79d01e7bd74cd37bad0249317a4dd431346",
            "messageTitle": "Level-3",
            "messageBody": "",
            "tags": [
              "Level-3"
            ],
            "fileTypesAndContributionMap": {
              "txt": {
                "insertions": 1,
                "deletions": 1
              },
              "java": {
                "insertions": 48,
                "deletions": 12
              }
            }
          },
          {
            "hash": "bdd1fc9b4d6397e6bbf1398cb8fb44489effa3d4",
            "messageTitle": "Level-4",
            "messageBody": "",
            "tags": [
              "Level-4"
            ],
            "fileTypesAndContributionMap": {
              "txt": {
                "insertions": 7,
                "deletions": 3
              },
              "java": {
                "insertions": 68,
                "deletions": 4
              }
            }
          },
          {
            "hash": "2255e4510de615d41ba2629a76d93eeff0d0ff71",
            "messageTitle": "A-TextUiTesting",
            "messageBody": "",
            "tags": [
              "A-TextUiTesting"
            ],
            "fileTypesAndContributionMap": {
              "txt": {
                "insertions": 4,
                "deletions": 1
              }
            }
          },
          {
            "hash": "efd895f9dfb164ff026bd70b45c6fe9cc7a0af38",
            "messageTitle": "Level-5",
            "messageBody": "",
            "tags": [
              "Level-5"
            ],
            "fileTypesAndContributionMap": {
              "txt": {
                "insertions": 9,
                "deletions": 6
              },
              "java": {
                "insertions": 145,
                "deletions": 39
              }
            }
          },
          {
            "hash": "f8502b2520a650eeda2d593105e10ef46202b647",
            "messageTitle": "Level-6",
            "messageBody": "",
            "fileTypesAndContributionMap": {
              "txt": {
                "insertions": 10,
                "deletions": 5
              },
              "java": {
                "insertions": 304,
                "deletions": 45
              }
            }
          },
          {
            "hash": "8dcf9bee451bfccc02940adc1d648d5f84ad2a97",
            "messageTitle": "Level-6",
            "messageBody": "",
            "tags": [
              "Level-6"
            ],
            "fileTypesAndContributionMap": {
              "txt": {
                "insertions": 1,
                "deletions": 0
              }
            }
          }
        ]
      },
      {
        "date": "2020-08-23",
        "commitResults": [
          {
            "hash": "b542383d867cf9cccc6203cdc4c210c4bebc5a64",
            "messageTitle": "Level-7, where TIMETABLE.TXT is updated whenever there is an update there and if it is absent there is a message to indicate that it has to be added.",
            "messageBody": "",
            "fileTypesAndContributionMap": {
              "txt": {
                "insertions": 4,
                "deletions": 10
              },
              "java": {
                "insertions": 161,
                "deletions": 115
              },
              "sh": {
                "insertions": 1,
                "deletions": 1
              }
            }
          },
          {
            "hash": "ceb0576ac156e8405f2f3f4dec5849dda385a085",
            "messageTitle": "Level-7, where TIMETABLE.TXT is updated whenever there is an update there and if it is absent there is a message to indicate that it has to be added.",
            "messageBody": "",
            "fileTypesAndContributionMap": {
              "txt": {
                "insertions": 2,
                "deletions": 0
              },
              "java": {
                "insertions": 2,
                "deletions": 2
              },
              "sh": {
                "insertions": 1,
                "deletions": 1
              }
            }
          },
          {
            "hash": "33ac7ebca1ad4a03f8e3b0e9649d93ef3f968b8f",
            "messageTitle": "Level-8, I have added the date and time details to this level.",
            "messageBody": "",
            "fileTypesAndContributionMap": {
              "txt": {
                "insertions": 1,
                "deletions": 10
              },
              "java": {
                "insertions": 207,
                "deletions": 9
              }
            }
          },
          {
            "hash": "b0413bf5c3959bd0c76bb8785e81ba588375a849",
            "messageTitle": "Level-7 and Level-8 are combined successfully",
            "messageBody": "",
            "fileTypesAndContributionMap": {
              "txt": {
                "insertions": 4,
                "deletions": 1
              },
              "java": {
                "insertions": 14,
                "deletions": 13
              }
            }
          }
        ]
      },
      {
        "date": "2020-08-24",
        "commitResults": [
          {
            "hash": "a978f74e65e11f70721f6433444ba7d997f67a83",
            "messageTitle": "Level-9 OOP implemented.",
            "messageBody": "",
            "fileTypesAndContributionMap": {
              "txt": {
                "insertions": 2,
                "deletions": 3
              },
              "java": {
                "insertions": 353,
                "deletions": 214
              }
            }
          },
          {
            "hash": "054138bdfe689408d2deeda4d01d9ec0ca9e0b5d",
            "messageTitle": "OOP implemented.",
            "messageBody": "",
            "fileTypesAndContributionMap": {
              "txt": {
                "insertions": 1,
                "deletions": 2
              },
              "java": {
                "insertions": 43,
                "deletions": 23
              }
            }
          },
          {
            "hash": "340737f8ed1def60c2418c347b8569b87dd68468",
            "messageTitle": "OOP implemented.",
            "messageBody": "",
            "fileTypesAndContributionMap": {
              "txt": {
                "insertions": 1,
                "deletions": 0
              },
              "java": {
                "insertions": 3,
                "deletions": 1
              }
            }
          },
          {
            "hash": "9f4c92ee2df36709c642f75bc1793ca847a7df49",
            "messageTitle": "Tested more than one class and they passed",
            "messageBody": "",
            "fileTypesAndContributionMap": {
              "txt": {
                "insertions": 27,
                "deletions": 14
              },
              "java": {
                "insertions": 395,
                "deletions": 179
              }
            }
          },
          {
            "hash": "2ba50f12fb0828c49ed34fffd62082077f9494ae",
            "messageTitle": "Tested more than one class and they passed",
            "messageBody": "",
            "fileTypesAndContributionMap": {
              "txt": {
                "insertions": 0,
                "deletions": 3
              },
              "java": {
                "insertions": 185,
                "deletions": 39
              }
            }
          },
          {
            "hash": "9a1e18a2fae8923ae2ea7c1407606eef2193b5af",
            "messageTitle": "Tested more than one class and they passed",
            "messageBody": "",
            "fileTypesAndContributionMap": {
              "txt": {
                "insertions": 4,
                "deletions": 0
              },
              "java": {
                "insertions": 30,
                "deletions": 38
              }
            }
          }
        ]
      },
      {
        "date": "2020-08-25",
        "commitResults": [
          {
            "hash": "dd2ca51366bc4d902382c9af13fb68768964bd07",
            "messageTitle": "More OOP final",
            "messageBody": "",
            "tags": [
              "A-MoreOOP"
            ],
            "fileTypesAndContributionMap": {
              "txt": {
                "insertions": 4,
                "deletions": 4
              },
              "java": {
                "insertions": 403,
                "deletions": 43
              }
            }
          },
          {
            "hash": "e97423a5336b15506ea297ea51dc7f012221dadb",
            "messageTitle": "javadoc done for more than half of public members",
            "messageBody": "",
            "fileTypesAndContributionMap": {
              "txt": {
                "insertions": 2,
                "deletions": 3
              },
              "java": {
                "insertions": 142,
                "deletions": 359
              }
            }
          },
          {
            "hash": "7de636d411844e3c63ead8374d56a42520dda85c",
            "messageTitle": "Level-9 with indentation rules followed",
            "messageBody": "",
            "fileTypesAndContributionMap": {
              "java": {
                "insertions": 76,
                "deletions": 1
              }
            }
          },
          {
            "hash": "47f828640e06e66daf8b73f4d3b24c2ee9038de8",
            "messageTitle": "Level-9 with indentation rules followed",
            "messageBody": "",
            "fileTypesAndContributionMap": {
              "java": {
                "insertions": 11,
                "deletions": 2
              }
            }
          },
          {
            "hash": "376198f519e4168deaef2882a6081d4addd91006",
            "messageTitle": "Level-9 with indentation rules followed",
            "messageBody": "",
            "fileTypesAndContributionMap": {
              "txt": {
                "insertions": 4,
                "deletions": 2
              },
              "java": {
                "insertions": 3,
                "deletions": 2
              }
            }
          },
          {
            "hash": "f0284fb3d57a7528cd313068c5628489bc402b96",
            "messageTitle": "Add Level-9 code",
            "messageBody": "For level 9, I have added a FindCommand class in Commands to complete the new find task.\n\nThen, there is another FindException class to handle the case where the keyword mentioned is absent or the keyword is absent.\n\nIf there are no exceptions, then different tasks in the currents tasks in taskList is being displayed.\n\nThen, the codes just typed in follows the coding style mentioned.\n",
            "fileTypesAndContributionMap": {
              "java": {
                "insertions": 25,
                "deletions": 14
              }
            }
          },
          {
            "hash": "a62c9b257afcacd952f22b67987aab0eaa8dbc27",
            "messageTitle": "Add J-Unit code",
            "messageBody": "Three different test cases where implemented to test out different scenarios and all of them passed.\n",
            "fileTypesAndContributionMap": {
              "txt": {
                "insertions": 132,
                "deletions": 5
              },
              "java": {
                "insertions": 98,
                "deletions": 108
              }
            }
          },
          {
            "hash": "34da23a4b585d433d0da81c50cb608b9f510b1ea",
            "messageTitle": "Add JavaDoc",
            "messageBody": "JavaDoc added for most members in most classes.\n",
            "fileTypesAndContributionMap": {
              "java": {
                "insertions": 222,
                "deletions": 39
              }
            }
          },
          {
            "hash": "bdde52a4d4c7e9156ceb0518811d90442dd49e26",
            "messageTitle": "Change code to follow code style",
            "messageBody": "Attempted to change current code to follow coding standards mentioned\n",
            "fileTypesAndContributionMap": {
              "java": {
                "insertions": 53,
                "deletions": 29
              }
            }
          },
          {
            "hash": "44168dfbdef7557feb90994b39650eab71236f5a",
            "messageTitle": "Level-9 clean",
            "messageBody": "Cleaned up the code and javaDoc of level 9.\n",
            "tags": [
              "A-Jar"
            ],
            "fileTypesAndContributionMap": {
              "java": {
                "insertions": 16,
                "deletions": 1
              }
            }
          },
          {
            "hash": "9573736fcc10528e4b7d2a3f8a7f20d14133aba3",
            "messageTitle": "A-JUnit test",
            "messageBody": "I have tested more than one class, with more than 2 methods and they passed\n",
            "tags": [
              "A-JUnit"
            ],
            "fileTypesAndContributionMap": {
              "txt": {
                "insertions": 2,
                "deletions": 2
              },
              "java": {
                "insertions": 8,
                "deletions": 116
              }
            }
          },
          {
            "hash": "4a08ebeed97da070b37732a55d3207271215003b",
            "messageTitle": "A-JavaDoc",
            "messageBody": "I have updated JavaDoc and made it clearer.\n",
            "fileTypesAndContributionMap": {
              "java": {
                "insertions": 10,
                "deletions": 13
              }
            }
          },
          {
            "hash": "dbc801edf638c43f299fa318162eece891b9bba4",
            "messageTitle": "A-CodingStandard",
            "messageBody": "I have adjusted code further to follow coding standard more closely\n",
            "fileTypesAndContributionMap": {
              "java": {
                "insertions": 6,
                "deletions": 4
              }
            }
          },
          {
            "hash": "fc0edbea2846f34f870251be2a30977b2be01a16",
            "messageTitle": "Level-9",
            "messageBody": "I have implemented the java class with coding standard followed and with javaDocs implemented there with correct coding standard.\n",
            "fileTypesAndContributionMap": {
              "txt": {
                "insertions": 3,
                "deletions": 2
              },
              "java": {
                "insertions": 116,
                "deletions": 4
              }
            }
          }
        ]
      },
      {
        "date": "2020-08-26",
        "commitResults": [
          {
            "hash": "b680aa1fc0ddd58b91292882e15c49a20321c35b",
            "messageTitle": "A-JavaDoc",
            "messageBody": "I have updated Java-Doc and made it more understandable.\n",
            "fileTypesAndContributionMap": {
              "java": {
                "insertions": 0,
                "deletions": 111
              }
            }
          },
          {
            "hash": "8b9d1415e8906819aec5c5032a282eb8680246e9",
            "messageTitle": "A-CodingStandard",
            "messageBody": "Adjusted code further to follow code style closely.\n",
            "fileTypesAndContributionMap": {
              "java": {
                "insertions": 0,
                "deletions": 1
              }
            }
          },
          {
            "hash": "9c81e9cb884e579642e73f7c11947e9afaa280d0",
            "messageTitle": "Level-9",
            "messageBody": "Added the find command to find out tasks containing keyword.\n",
            "fileTypesAndContributionMap": {
              "java": {
                "insertions": 1,
                "deletions": 1
              }
            }
          },
          {
            "hash": "45175f50e37053db89098868b6c1769961659772",
            "messageTitle": "A-JavaDoc",
            "messageBody": "Updated javaDoc for easier readability.\n",
            "fileTypesAndContributionMap": {
              "java": {
                "insertions": 1,
                "deletions": 1
              }
            }
          },
          {
            "hash": "0fb9344b2a7c58ba84750f2f7e22ad9b99ce1754",
            "messageTitle": "A-CodingStandard",
            "messageBody": "I have changed code further, to make it seem as if one person has written it which is one of the guidelines to follow according to coding standards provided.\n",
            "fileTypesAndContributionMap": {
              "java": {
                "insertions": 4,
                "deletions": 4
              }
            }
          },
          {
            "hash": "71237e05faf052b9b0b0ac24ddf7c905c6cc98b2",
            "messageTitle": "Level-9",
            "messageBody": "Added the code for level 9, which is used to give the list of tasks containing the keywords after find or throwing error if no keyword\nis present or such keywords is not found in the TaskList.\n",
            "fileTypesAndContributionMap": {
              "java": {
                "insertions": 112,
                "deletions": 2
              }
            }
          }
        ]
      },
      {
        "date": "2020-08-30",
        "commitResults": [
          {
            "hash": "27a2c11789e8a82b1778400d244a712537cfba74",
            "messageTitle": "Add A-Gradle",
            "messageBody": "I have set up gradle such that I can build and run Duke using gradle, where I used it to extend my current tasks list.\n",
            "fileTypesAndContributionMap": {
              "txt": {
                "insertions": 4,
                "deletions": 3
              }
            }
          },
          {
            "hash": "5da5ca6f83c108daa0cc63469d81f1fa401df941",
            "messageTitle": "Add A-Gradle",
            "messageBody": "I have used gradle to run J-Unit test as well, completing the recommended part.\n",
            "fileTypesAndContributionMap": {
              "txt": {
                "insertions": 2,
                "deletions": 4
              },
              "java": {
                "insertions": 12,
                "deletions": 8
              }
            }
          }
        ]
      },
      {
        "date": "2020-08-31",
        "commitResults": [
          {
            "hash": "5313476479d4d0d1740bb9dd79ee5aaf141d2327",
            "messageTitle": "Add Level-10",
            "messageBody": "I have successfully made a GUI for my Duke app using JavaFX.\n",
            "fileTypesAndContributionMap": {
              "gradle": {
                "insertions": 15,
                "deletions": 0
              },
              "txt": {
                "insertions": 4,
                "deletions": 1
              },
              "fxml": {
                "insertions": 33,
                "deletions": 0
              },
              "java": {
                "insertions": 385,
                "deletions": 43
              }
            }
          }
        ]
      },
      {
        "date": "2020-09-01",
        "commitResults": [
          {
            "hash": "032b2c1f67627b401f1105b200a51995b097ede2",
            "messageTitle": "Add Level-10",
            "messageBody": "Make some changes to my coding style as well.\n\nMake changes to my Level-10 as my in previous commit not all of my output could be seen if the length exceeds the screen length.\n",
            "fileTypesAndContributionMap": {
              "txt": {
                "insertions": 4,
                "deletions": 1
              },
              "fxml": {
                "insertions": 2,
                "deletions": 1
              },
              "java": {
                "insertions": 133,
                "deletions": 253
              }
            }
          },
          {
            "hash": "975d0372aae57a4a8c3fd76dddaee5f37da88c27",
            "messageTitle": "Small changes",
            "messageBody": "Make some more changes to improve code quality.\n",
            "fileTypesAndContributionMap": {
              "java": {
                "insertions": 49,
                "deletions": 45
              }
            }
          },
          {
            "hash": "567fbcd12cc1e8dc9037d7690753049a88ebbdc6",
            "messageTitle": "Add Level-10",
            "messageBody": "My app closes by itself once you add an additional input after bye, the app exits. Furthermore, it also greets the user when opens.\n",
            "fileTypesAndContributionMap": {
              "fxml": {
                "insertions": 3,
                "deletions": 2
              },
              "java": {
                "insertions": 39,
                "deletions": 31
              }
            }
          },
          {
            "hash": "c7641a6bf68b306ba75486174546af880a5860f5",
            "messageTitle": "Add Level-10",
            "messageBody": "Made small changes and added JavaDoc comments.\n",
            "fileTypesAndContributionMap": {
              "java": {
                "insertions": 41,
                "deletions": 9
              }
            }
          },
          {
            "hash": "11906d7588e0a8fc216162d702886ba355f09eed",
            "messageTitle": "Add A-Varargs",
            "messageBody": "Added inputs in Duke class such that the user can add more than one input and Duke could give different outputs for the different inputs given\n",
            "fileTypesAndContributionMap": {
              "java": {
                "insertions": 15,
                "deletions": 9
              }
            }
          },
          {
            "hash": "5553ef9974d392c5785d4f4b74fcfa6653338327",
            "messageTitle": "Add A-Varargs",
            "messageBody": "Small changes made and made changes to JavaDoc\n",
            "fileTypesAndContributionMap": {
              "java": {
                "insertions": 2,
                "deletions": 2
              }
            }
          },
          {
            "hash": "f0d73dc21f06c77bc274b8f5045e0c1fedfa3959",
            "messageTitle": "Make Minor changes",
            "messageBody": "Adjusted code to comply with coding style better.\n",
            "fileTypesAndContributionMap": {
              "java": {
                "insertions": 111,
                "deletions": 55
              }
            }
          }
        ]
      }
    ]
  },
  "authorFileTypeContributionMap": {
    "itssodium": {
      "java": 2058,
      "md": 0,
      "fxml": 35,
      "sh": 7,
      "bat": 0,
      "gradle": 15,
      "txt": 162
    }
  },
  "authorContributionVariance": {
    "itssodium": 389337.78
  },
  "authorDisplayNameMap": {
    "itssodium": "CS2103T-W12-1 NOOR.. H U"
  }
}
