[
  {
    "path": "src/main/java/Deadline.java",
    "fileType": "java",
    "lines": [
      {
        "lineNumber": 1,
        "author": {
          "gitId": "silvernitro"
        },
        "content": "public class Deadline  extends Task {"
      },
      {
        "lineNumber": 2,
        "author": {
          "gitId": "silvernitro"
        },
        "content": "    private String date;"
      },
      {
        "lineNumber": 3,
        "author": {
          "gitId": "silvernitro"
        },
        "content": ""
      },
      {
        "lineNumber": 4,
        "author": {
          "gitId": "silvernitro"
        },
        "content": "    Deadline(String description, String date) {"
      },
      {
        "lineNumber": 5,
        "author": {
          "gitId": "silvernitro"
        },
        "content": "        super(description);"
      },
      {
        "lineNumber": 6,
        "author": {
          "gitId": "silvernitro"
        },
        "content": "        this.date \u003d date;"
      },
      {
        "lineNumber": 7,
        "author": {
          "gitId": "silvernitro"
        },
        "content": "    }"
      },
      {
        "lineNumber": 8,
        "author": {
          "gitId": "silvernitro"
        },
        "content": ""
      },
      {
        "lineNumber": 9,
        "author": {
          "gitId": "silvernitro"
        },
        "content": "    @Override"
      },
      {
        "lineNumber": 10,
        "author": {
          "gitId": "silvernitro"
        },
        "content": "    public String toString() {"
      },
      {
        "lineNumber": 11,
        "author": {
          "gitId": "silvernitro"
        },
        "content": "        return \"[D] \" + super.toString() + \" (by: \" + date + \")\";"
      },
      {
        "lineNumber": 12,
        "author": {
          "gitId": "silvernitro"
        },
        "content": "    }"
      },
      {
        "lineNumber": 13,
        "author": {
          "gitId": "silvernitro"
        },
        "content": "}"
      }
    ],
    "authorContributionMap": {
      "silvernitro": 13
    }
  },
  {
    "path": "src/main/java/Duke.java",
    "fileType": "java",
    "lines": [
      {
        "lineNumber": 1,
        "author": {
          "gitId": "silvernitro"
        },
        "content": "import java.io.IOException;"
      },
      {
        "lineNumber": 2,
        "author": {
          "gitId": "silvernitro"
        },
        "content": ""
      },
      {
        "lineNumber": 3,
        "author": {
          "gitId": "-"
        },
        "content": "public class Duke {"
      },
      {
        "lineNumber": 4,
        "author": {
          "gitId": "-"
        },
        "content": "    public static void main(String[] args) {"
      },
      {
        "lineNumber": 5,
        "author": {
          "gitId": "silvernitro"
        },
        "content": "        System.out.println(\"Hi I\u0027m Duke, your personal task-tracker bot!\");"
      },
      {
        "lineNumber": 6,
        "author": {
          "gitId": "silvernitro"
        },
        "content": "        System.out.println(\"You can add todos, deadlines, or events to my \" +"
      },
      {
        "lineNumber": 7,
        "author": {
          "gitId": "silvernitro"
        },
        "content": "                                   \"list.\");"
      },
      {
        "lineNumber": 8,
        "author": {
          "gitId": "silvernitro"
        },
        "content": ""
      },
      {
        "lineNumber": 9,
        "author": {
          "gitId": "silvernitro"
        },
        "content": "        try {"
      },
      {
        "lineNumber": 10,
        "author": {
          "gitId": "silvernitro"
        },
        "content": "            Scanner.scan();"
      },
      {
        "lineNumber": 11,
        "author": {
          "gitId": "silvernitro"
        },
        "content": "        } catch (IOException exception) {"
      },
      {
        "lineNumber": 12,
        "author": {
          "gitId": "silvernitro"
        },
        "content": "            System.out.println(\"An exception occurred:\");"
      },
      {
        "lineNumber": 13,
        "author": {
          "gitId": "silvernitro"
        },
        "content": "            System.out.println(exception.getMessage());"
      },
      {
        "lineNumber": 14,
        "author": {
          "gitId": "silvernitro"
        },
        "content": "        }"
      },
      {
        "lineNumber": 15,
        "author": {
          "gitId": "-"
        },
        "content": "    }"
      },
      {
        "lineNumber": 16,
        "author": {
          "gitId": "-"
        },
        "content": "}"
      }
    ],
    "authorContributionMap": {
      "silvernitro": 12,
      "-": 4
    }
  },
  {
    "path": "src/main/java/DukeException.java",
    "fileType": "java",
    "lines": [
      {
        "lineNumber": 1,
        "author": {
          "gitId": "silvernitro"
        },
        "content": "public class DukeException extends Exception {"
      },
      {
        "lineNumber": 2,
        "author": {
          "gitId": "silvernitro"
        },
        "content": "    DukeException(String message) {"
      },
      {
        "lineNumber": 3,
        "author": {
          "gitId": "silvernitro"
        },
        "content": "        super(message);"
      },
      {
        "lineNumber": 4,
        "author": {
          "gitId": "silvernitro"
        },
        "content": "    }"
      },
      {
        "lineNumber": 5,
        "author": {
          "gitId": "silvernitro"
        },
        "content": ""
      },
      {
        "lineNumber": 6,
        "author": {
          "gitId": "silvernitro"
        },
        "content": "    DukeException(String message, Throwable err) {"
      },
      {
        "lineNumber": 7,
        "author": {
          "gitId": "silvernitro"
        },
        "content": "        super(message, err);"
      },
      {
        "lineNumber": 8,
        "author": {
          "gitId": "silvernitro"
        },
        "content": "    }"
      },
      {
        "lineNumber": 9,
        "author": {
          "gitId": "silvernitro"
        },
        "content": "}"
      }
    ],
    "authorContributionMap": {
      "silvernitro": 9
    }
  },
  {
    "path": "src/main/java/Event.java",
    "fileType": "java",
    "lines": [
      {
        "lineNumber": 1,
        "author": {
          "gitId": "silvernitro"
        },
        "content": "public class Event extends Task {"
      },
      {
        "lineNumber": 2,
        "author": {
          "gitId": "silvernitro"
        },
        "content": "    private String date;"
      },
      {
        "lineNumber": 3,
        "author": {
          "gitId": "silvernitro"
        },
        "content": ""
      },
      {
        "lineNumber": 4,
        "author": {
          "gitId": "silvernitro"
        },
        "content": "    Event(String description, String date) {"
      },
      {
        "lineNumber": 5,
        "author": {
          "gitId": "silvernitro"
        },
        "content": "        super(description);"
      },
      {
        "lineNumber": 6,
        "author": {
          "gitId": "silvernitro"
        },
        "content": "        this.date \u003d date;"
      },
      {
        "lineNumber": 7,
        "author": {
          "gitId": "silvernitro"
        },
        "content": "    }"
      },
      {
        "lineNumber": 8,
        "author": {
          "gitId": "silvernitro"
        },
        "content": ""
      },
      {
        "lineNumber": 9,
        "author": {
          "gitId": "silvernitro"
        },
        "content": "    @Override"
      },
      {
        "lineNumber": 10,
        "author": {
          "gitId": "silvernitro"
        },
        "content": "    public String toString() {"
      },
      {
        "lineNumber": 11,
        "author": {
          "gitId": "silvernitro"
        },
        "content": "        return \"[E] \" + super.toString() + \" (at: \" + date  + \")\";"
      },
      {
        "lineNumber": 12,
        "author": {
          "gitId": "silvernitro"
        },
        "content": "    }"
      },
      {
        "lineNumber": 13,
        "author": {
          "gitId": "silvernitro"
        },
        "content": "}"
      }
    ],
    "authorContributionMap": {
      "silvernitro": 13
    }
  },
  {
    "path": "src/main/java/Scanner.java",
    "fileType": "java",
    "lines": [
      {
        "lineNumber": 1,
        "author": {
          "gitId": "silvernitro"
        },
        "content": "import java.util.Arrays;"
      },
      {
        "lineNumber": 2,
        "author": {
          "gitId": "silvernitro"
        },
        "content": "import java.util.List;"
      },
      {
        "lineNumber": 3,
        "author": {
          "gitId": "silvernitro"
        },
        "content": "import java.io.BufferedReader;"
      },
      {
        "lineNumber": 4,
        "author": {
          "gitId": "silvernitro"
        },
        "content": "import java.io.IOException;"
      },
      {
        "lineNumber": 5,
        "author": {
          "gitId": "silvernitro"
        },
        "content": "import java.io.InputStreamReader;"
      },
      {
        "lineNumber": 6,
        "author": {
          "gitId": "silvernitro"
        },
        "content": ""
      },
      {
        "lineNumber": 7,
        "author": {
          "gitId": "silvernitro"
        },
        "content": "public class Scanner {"
      },
      {
        "lineNumber": 8,
        "author": {
          "gitId": "silvernitro"
        },
        "content": "    // array of valid commands"
      },
      {
        "lineNumber": 9,
        "author": {
          "gitId": "silvernitro"
        },
        "content": "    private final static List\u003cString\u003e COMMANDS \u003d Arrays.asList(\"done\","
      },
      {
        "lineNumber": 10,
        "author": {
          "gitId": "silvernitro"
        },
        "content": "                                                               \"delete\");"
      },
      {
        "lineNumber": 11,
        "author": {
          "gitId": "silvernitro"
        },
        "content": ""
      },
      {
        "lineNumber": 12,
        "author": {
          "gitId": "silvernitro"
        },
        "content": "    static void scan() throws IOException {"
      },
      {
        "lineNumber": 13,
        "author": {
          "gitId": "silvernitro"
        },
        "content": "        BufferedReader reader \u003d"
      },
      {
        "lineNumber": 14,
        "author": {
          "gitId": "silvernitro"
        },
        "content": "                new BufferedReader(new InputStreamReader((System.in)));"
      },
      {
        "lineNumber": 15,
        "author": {
          "gitId": "silvernitro"
        },
        "content": "        TaskList userTaskList \u003d new TaskList();"
      },
      {
        "lineNumber": 16,
        "author": {
          "gitId": "silvernitro"
        },
        "content": ""
      },
      {
        "lineNumber": 17,
        "author": {
          "gitId": "silvernitro"
        },
        "content": "        scanLoop:"
      },
      {
        "lineNumber": 18,
        "author": {
          "gitId": "silvernitro"
        },
        "content": "        while(true) {"
      },
      {
        "lineNumber": 19,
        "author": {
          "gitId": "silvernitro"
        },
        "content": "            String line \u003d reader.readLine();"
      },
      {
        "lineNumber": 20,
        "author": {
          "gitId": "silvernitro"
        },
        "content": "            String command \u003d line.split(\" \")[0];"
      },
      {
        "lineNumber": 21,
        "author": {
          "gitId": "silvernitro"
        },
        "content": ""
      },
      {
        "lineNumber": 22,
        "author": {
          "gitId": "silvernitro"
        },
        "content": "            if (COMMANDS.contains(command) \u0026\u0026 line.split(\" \").length \u003e 1) {"
      },
      {
        "lineNumber": 23,
        "author": {
          "gitId": "silvernitro"
        },
        "content": "                // handle commands with \u003e1 argument"
      },
      {
        "lineNumber": 24,
        "author": {
          "gitId": "silvernitro"
        },
        "content": "                switch (command) {"
      },
      {
        "lineNumber": 25,
        "author": {
          "gitId": "silvernitro"
        },
        "content": "                    case \"done\":"
      },
      {
        "lineNumber": 26,
        "author": {
          "gitId": "silvernitro"
        },
        "content": "                        try {"
      },
      {
        "lineNumber": 27,
        "author": {
          "gitId": "silvernitro"
        },
        "content": "                            userTaskList.markAsDone("
      },
      {
        "lineNumber": 28,
        "author": {
          "gitId": "silvernitro"
        },
        "content": "                                    Integer.parseInt(line.split( \" \")[1])"
      },
      {
        "lineNumber": 29,
        "author": {
          "gitId": "silvernitro"
        },
        "content": "                            );"
      },
      {
        "lineNumber": 30,
        "author": {
          "gitId": "silvernitro"
        },
        "content": "                        } catch (IllegalArgumentException ex) {"
      },
      {
        "lineNumber": 31,
        "author": {
          "gitId": "silvernitro"
        },
        "content": "                            System.out.println(ex.getMessage());"
      },
      {
        "lineNumber": 32,
        "author": {
          "gitId": "silvernitro"
        },
        "content": "                        }"
      },
      {
        "lineNumber": 33,
        "author": {
          "gitId": "silvernitro"
        },
        "content": "                        break;"
      },
      {
        "lineNumber": 34,
        "author": {
          "gitId": "silvernitro"
        },
        "content": "                    case \"delete\":"
      },
      {
        "lineNumber": 35,
        "author": {
          "gitId": "silvernitro"
        },
        "content": "                        try {"
      },
      {
        "lineNumber": 36,
        "author": {
          "gitId": "silvernitro"
        },
        "content": "                            userTaskList.removeItem("
      },
      {
        "lineNumber": 37,
        "author": {
          "gitId": "silvernitro"
        },
        "content": "                                    Integer.parseInt(line.split( \" \")[1])"
      },
      {
        "lineNumber": 38,
        "author": {
          "gitId": "silvernitro"
        },
        "content": "                            );"
      },
      {
        "lineNumber": 39,
        "author": {
          "gitId": "silvernitro"
        },
        "content": "                        } catch (IllegalArgumentException ex) {"
      },
      {
        "lineNumber": 40,
        "author": {
          "gitId": "silvernitro"
        },
        "content": "                            System.out.println(ex.getMessage());"
      },
      {
        "lineNumber": 41,
        "author": {
          "gitId": "silvernitro"
        },
        "content": "                        }"
      },
      {
        "lineNumber": 42,
        "author": {
          "gitId": "silvernitro"
        },
        "content": "                        break;"
      },
      {
        "lineNumber": 43,
        "author": {
          "gitId": "silvernitro"
        },
        "content": "                    default:"
      },
      {
        "lineNumber": 44,
        "author": {
          "gitId": "silvernitro"
        },
        "content": "                        break;"
      },
      {
        "lineNumber": 45,
        "author": {
          "gitId": "silvernitro"
        },
        "content": "                }"
      },
      {
        "lineNumber": 46,
        "author": {
          "gitId": "silvernitro"
        },
        "content": "            } else {"
      },
      {
        "lineNumber": 47,
        "author": {
          "gitId": "silvernitro"
        },
        "content": "                switch(line) {"
      },
      {
        "lineNumber": 48,
        "author": {
          "gitId": "silvernitro"
        },
        "content": "                    case \"bye\":"
      },
      {
        "lineNumber": 49,
        "author": {
          "gitId": "silvernitro"
        },
        "content": "                        System.out.println(\"Bye. Hope to see you again\");"
      },
      {
        "lineNumber": 50,
        "author": {
          "gitId": "silvernitro"
        },
        "content": "                        break scanLoop;"
      },
      {
        "lineNumber": 51,
        "author": {
          "gitId": "silvernitro"
        },
        "content": "                    case \"list\":"
      },
      {
        "lineNumber": 52,
        "author": {
          "gitId": "silvernitro"
        },
        "content": "                        userTaskList.printList();"
      },
      {
        "lineNumber": 53,
        "author": {
          "gitId": "silvernitro"
        },
        "content": "                        break;"
      },
      {
        "lineNumber": 54,
        "author": {
          "gitId": "silvernitro"
        },
        "content": "                    default:"
      },
      {
        "lineNumber": 55,
        "author": {
          "gitId": "silvernitro"
        },
        "content": "                        try {"
      },
      {
        "lineNumber": 56,
        "author": {
          "gitId": "silvernitro"
        },
        "content": "                            Task addedTask \u003d userTaskList.addItem(line);"
      },
      {
        "lineNumber": 57,
        "author": {
          "gitId": "silvernitro"
        },
        "content": "                            System.out.println(\"added: \" + addedTask);"
      },
      {
        "lineNumber": 58,
        "author": {
          "gitId": "silvernitro"
        },
        "content": "                        } catch (DukeException ex) {"
      },
      {
        "lineNumber": 59,
        "author": {
          "gitId": "silvernitro"
        },
        "content": "                            System.out.println(ex.getMessage());"
      },
      {
        "lineNumber": 60,
        "author": {
          "gitId": "silvernitro"
        },
        "content": "                        }"
      },
      {
        "lineNumber": 61,
        "author": {
          "gitId": "silvernitro"
        },
        "content": "                        break;"
      },
      {
        "lineNumber": 62,
        "author": {
          "gitId": "silvernitro"
        },
        "content": "                }"
      },
      {
        "lineNumber": 63,
        "author": {
          "gitId": "silvernitro"
        },
        "content": "            }"
      },
      {
        "lineNumber": 64,
        "author": {
          "gitId": "silvernitro"
        },
        "content": "        }"
      },
      {
        "lineNumber": 65,
        "author": {
          "gitId": "silvernitro"
        },
        "content": "    }"
      },
      {
        "lineNumber": 66,
        "author": {
          "gitId": "silvernitro"
        },
        "content": "}"
      }
    ],
    "authorContributionMap": {
      "silvernitro": 66
    }
  },
  {
    "path": "src/main/java/Task.java",
    "fileType": "java",
    "lines": [
      {
        "lineNumber": 1,
        "author": {
          "gitId": "silvernitro"
        },
        "content": "public class Task {"
      },
      {
        "lineNumber": 2,
        "author": {
          "gitId": "silvernitro"
        },
        "content": "    private final String taskDescription;"
      },
      {
        "lineNumber": 3,
        "author": {
          "gitId": "silvernitro"
        },
        "content": "    private boolean isDone \u003d false;"
      },
      {
        "lineNumber": 4,
        "author": {
          "gitId": "silvernitro"
        },
        "content": ""
      },
      {
        "lineNumber": 5,
        "author": {
          "gitId": "silvernitro"
        },
        "content": "    Task(String description) {"
      },
      {
        "lineNumber": 6,
        "author": {
          "gitId": "silvernitro"
        },
        "content": "        taskDescription \u003d description;"
      },
      {
        "lineNumber": 7,
        "author": {
          "gitId": "silvernitro"
        },
        "content": "    }"
      },
      {
        "lineNumber": 8,
        "author": {
          "gitId": "silvernitro"
        },
        "content": ""
      },
      {
        "lineNumber": 9,
        "author": {
          "gitId": "silvernitro"
        },
        "content": "    void markAsDone() {"
      },
      {
        "lineNumber": 10,
        "author": {
          "gitId": "silvernitro"
        },
        "content": "       this.isDone \u003d true;"
      },
      {
        "lineNumber": 11,
        "author": {
          "gitId": "silvernitro"
        },
        "content": "       System.out.println(\"I\u0027ve marked this task as done:\\n\" + toString());"
      },
      {
        "lineNumber": 12,
        "author": {
          "gitId": "silvernitro"
        },
        "content": "    }"
      },
      {
        "lineNumber": 13,
        "author": {
          "gitId": "silvernitro"
        },
        "content": ""
      },
      {
        "lineNumber": 14,
        "author": {
          "gitId": "silvernitro"
        },
        "content": "    public String toString() {"
      },
      {
        "lineNumber": 15,
        "author": {
          "gitId": "silvernitro"
        },
        "content": "        String status \u003d isDone ? \"\\u2713\" : \"\\u2718\";"
      },
      {
        "lineNumber": 16,
        "author": {
          "gitId": "silvernitro"
        },
        "content": "        return \"[\" + status + \"] \" + taskDescription;"
      },
      {
        "lineNumber": 17,
        "author": {
          "gitId": "silvernitro"
        },
        "content": "    }"
      },
      {
        "lineNumber": 18,
        "author": {
          "gitId": "silvernitro"
        },
        "content": "}"
      }
    ],
    "authorContributionMap": {
      "silvernitro": 18
    }
  },
  {
    "path": "src/main/java/TaskList.java",
    "fileType": "java",
    "lines": [
      {
        "lineNumber": 1,
        "author": {
          "gitId": "silvernitro"
        },
        "content": "import java.util.List;"
      },
      {
        "lineNumber": 2,
        "author": {
          "gitId": "silvernitro"
        },
        "content": "import java.util.ArrayList;"
      },
      {
        "lineNumber": 3,
        "author": {
          "gitId": "silvernitro"
        },
        "content": ""
      },
      {
        "lineNumber": 4,
        "author": {
          "gitId": "silvernitro"
        },
        "content": "public class TaskList {"
      },
      {
        "lineNumber": 5,
        "author": {
          "gitId": "silvernitro"
        },
        "content": "    private final List\u003cTask\u003e itemList \u003d new ArrayList\u003c\u003e();"
      },
      {
        "lineNumber": 6,
        "author": {
          "gitId": "silvernitro"
        },
        "content": ""
      },
      {
        "lineNumber": 7,
        "author": {
          "gitId": "silvernitro"
        },
        "content": "    Task addItem(String item) throws DukeException {"
      },
      {
        "lineNumber": 8,
        "author": {
          "gitId": "silvernitro"
        },
        "content": "        String type \u003d getItemType(item);"
      },
      {
        "lineNumber": 9,
        "author": {
          "gitId": "silvernitro"
        },
        "content": "        Task taskToAdd \u003d null;"
      },
      {
        "lineNumber": 10,
        "author": {
          "gitId": "silvernitro"
        },
        "content": "        switch(type) {"
      },
      {
        "lineNumber": 11,
        "author": {
          "gitId": "silvernitro"
        },
        "content": "            case \"todo\":"
      },
      {
        "lineNumber": 12,
        "author": {
          "gitId": "silvernitro"
        },
        "content": "                if (item.trim().equals(\"todo\")) {"
      },
      {
        "lineNumber": 13,
        "author": {
          "gitId": "silvernitro"
        },
        "content": "                    throw new DukeException(\"Todos must have non-empty \" +"
      },
      {
        "lineNumber": 14,
        "author": {
          "gitId": "silvernitro"
        },
        "content": "                                                    \"descriptions!\");"
      },
      {
        "lineNumber": 15,
        "author": {
          "gitId": "silvernitro"
        },
        "content": "                }"
      },
      {
        "lineNumber": 16,
        "author": {
          "gitId": "silvernitro"
        },
        "content": ""
      },
      {
        "lineNumber": 17,
        "author": {
          "gitId": "silvernitro"
        },
        "content": "                String todoDescription \u003d item.split(\"todo\")[1].trim();"
      },
      {
        "lineNumber": 18,
        "author": {
          "gitId": "silvernitro"
        },
        "content": "                taskToAdd \u003d new Todo(todoDescription);"
      },
      {
        "lineNumber": 19,
        "author": {
          "gitId": "silvernitro"
        },
        "content": "                break;"
      },
      {
        "lineNumber": 20,
        "author": {
          "gitId": "silvernitro"
        },
        "content": "            case \"deadline\":"
      },
      {
        "lineNumber": 21,
        "author": {
          "gitId": "silvernitro"
        },
        "content": "                taskToAdd \u003d new Deadline("
      },
      {
        "lineNumber": 22,
        "author": {
          "gitId": "silvernitro"
        },
        "content": "                        getItemDescription(item, type),"
      },
      {
        "lineNumber": 23,
        "author": {
          "gitId": "silvernitro"
        },
        "content": "                        getItemParameter(item, type)"
      },
      {
        "lineNumber": 24,
        "author": {
          "gitId": "silvernitro"
        },
        "content": "                );"
      },
      {
        "lineNumber": 25,
        "author": {
          "gitId": "silvernitro"
        },
        "content": "                break;"
      },
      {
        "lineNumber": 26,
        "author": {
          "gitId": "silvernitro"
        },
        "content": "            case \"event\":"
      },
      {
        "lineNumber": 27,
        "author": {
          "gitId": "silvernitro"
        },
        "content": "                taskToAdd \u003d new Event("
      },
      {
        "lineNumber": 28,
        "author": {
          "gitId": "silvernitro"
        },
        "content": "                        getItemDescription(item, type),"
      },
      {
        "lineNumber": 29,
        "author": {
          "gitId": "silvernitro"
        },
        "content": "                        getItemParameter(item, type)"
      },
      {
        "lineNumber": 30,
        "author": {
          "gitId": "silvernitro"
        },
        "content": "                );"
      },
      {
        "lineNumber": 31,
        "author": {
          "gitId": "silvernitro"
        },
        "content": "                break;"
      },
      {
        "lineNumber": 32,
        "author": {
          "gitId": "silvernitro"
        },
        "content": "            default:"
      },
      {
        "lineNumber": 33,
        "author": {
          "gitId": "silvernitro"
        },
        "content": "                throw new DukeException(\"Unrecognized task/command.\");"
      },
      {
        "lineNumber": 34,
        "author": {
          "gitId": "silvernitro"
        },
        "content": "        }"
      },
      {
        "lineNumber": 35,
        "author": {
          "gitId": "silvernitro"
        },
        "content": ""
      },
      {
        "lineNumber": 36,
        "author": {
          "gitId": "silvernitro"
        },
        "content": ""
      },
      {
        "lineNumber": 37,
        "author": {
          "gitId": "silvernitro"
        },
        "content": "        itemList.add(taskToAdd);"
      },
      {
        "lineNumber": 38,
        "author": {
          "gitId": "silvernitro"
        },
        "content": "        return taskToAdd;"
      },
      {
        "lineNumber": 39,
        "author": {
          "gitId": "silvernitro"
        },
        "content": "    }"
      },
      {
        "lineNumber": 40,
        "author": {
          "gitId": "silvernitro"
        },
        "content": ""
      },
      {
        "lineNumber": 41,
        "author": {
          "gitId": "silvernitro"
        },
        "content": "    //--------start of item literal parsers---------//"
      },
      {
        "lineNumber": 42,
        "author": {
          "gitId": "silvernitro"
        },
        "content": "    String getItemType(String item) {"
      },
      {
        "lineNumber": 43,
        "author": {
          "gitId": "silvernitro"
        },
        "content": "        return item.split(\" \")[0].trim();"
      },
      {
        "lineNumber": 44,
        "author": {
          "gitId": "silvernitro"
        },
        "content": "    }"
      },
      {
        "lineNumber": 45,
        "author": {
          "gitId": "silvernitro"
        },
        "content": ""
      },
      {
        "lineNumber": 46,
        "author": {
          "gitId": "silvernitro"
        },
        "content": "    String getItemDescription(String item, String itemType) {"
      },
      {
        "lineNumber": 47,
        "author": {
          "gitId": "silvernitro"
        },
        "content": "        // remove itemtype, which is the first word of the item literal"
      },
      {
        "lineNumber": 48,
        "author": {
          "gitId": "silvernitro"
        },
        "content": "        return splitItemLiteral(item, itemType)[0]"
      },
      {
        "lineNumber": 49,
        "author": {
          "gitId": "silvernitro"
        },
        "content": "                .split(itemType)[1]"
      },
      {
        "lineNumber": 50,
        "author": {
          "gitId": "silvernitro"
        },
        "content": "                .trim();"
      },
      {
        "lineNumber": 51,
        "author": {
          "gitId": "silvernitro"
        },
        "content": "    }"
      },
      {
        "lineNumber": 52,
        "author": {
          "gitId": "silvernitro"
        },
        "content": ""
      },
      {
        "lineNumber": 53,
        "author": {
          "gitId": "silvernitro"
        },
        "content": "    String getItemParameter(String item, String itemType) {"
      },
      {
        "lineNumber": 54,
        "author": {
          "gitId": "silvernitro"
        },
        "content": "        return splitItemLiteral(item, itemType)[1].trim();"
      },
      {
        "lineNumber": 55,
        "author": {
          "gitId": "silvernitro"
        },
        "content": "    }"
      },
      {
        "lineNumber": 56,
        "author": {
          "gitId": "silvernitro"
        },
        "content": ""
      },
      {
        "lineNumber": 57,
        "author": {
          "gitId": "silvernitro"
        },
        "content": "    String[] splitItemLiteral(String item, String itemType) {"
      },
      {
        "lineNumber": 58,
        "author": {
          "gitId": "silvernitro"
        },
        "content": "        String delimiter \u003d itemType.equals(\"deadline\") ? \"/by\" : \"/at\";"
      },
      {
        "lineNumber": 59,
        "author": {
          "gitId": "silvernitro"
        },
        "content": "        return item.split(delimiter);"
      },
      {
        "lineNumber": 60,
        "author": {
          "gitId": "silvernitro"
        },
        "content": "    }"
      },
      {
        "lineNumber": 61,
        "author": {
          "gitId": "silvernitro"
        },
        "content": "    //--------end of item literal parsers---------//"
      },
      {
        "lineNumber": 62,
        "author": {
          "gitId": "silvernitro"
        },
        "content": ""
      },
      {
        "lineNumber": 63,
        "author": {
          "gitId": "silvernitro"
        },
        "content": "    void markAsDone(int itemIndex) throws IllegalArgumentException {"
      },
      {
        "lineNumber": 64,
        "author": {
          "gitId": "silvernitro"
        },
        "content": "        if (itemIndex \u003e itemList.size()) {"
      },
      {
        "lineNumber": 65,
        "author": {
          "gitId": "silvernitro"
        },
        "content": "            throw new IllegalArgumentException(\"Item #\" + itemIndex + \" does \" +"
      },
      {
        "lineNumber": 66,
        "author": {
          "gitId": "silvernitro"
        },
        "content": "                                                       \"not exist and cannot \" +"
      },
      {
        "lineNumber": 67,
        "author": {
          "gitId": "silvernitro"
        },
        "content": "                                                       \"be marked as done.\");"
      },
      {
        "lineNumber": 68,
        "author": {
          "gitId": "silvernitro"
        },
        "content": "        }"
      },
      {
        "lineNumber": 69,
        "author": {
          "gitId": "silvernitro"
        },
        "content": "        itemList.get(itemIndex - 1).markAsDone();"
      },
      {
        "lineNumber": 70,
        "author": {
          "gitId": "silvernitro"
        },
        "content": "    }"
      },
      {
        "lineNumber": 71,
        "author": {
          "gitId": "silvernitro"
        },
        "content": ""
      },
      {
        "lineNumber": 72,
        "author": {
          "gitId": "silvernitro"
        },
        "content": "    void removeItem(int itemIndex) throws IllegalArgumentException {"
      },
      {
        "lineNumber": 73,
        "author": {
          "gitId": "silvernitro"
        },
        "content": "        if (itemIndex \u003e itemList.size()) {"
      },
      {
        "lineNumber": 74,
        "author": {
          "gitId": "silvernitro"
        },
        "content": "            throw new IllegalArgumentException(\"Item #\" + itemIndex + \" does \" +"
      },
      {
        "lineNumber": 75,
        "author": {
          "gitId": "silvernitro"
        },
        "content": "                                                       \"not exist and cannot \" +"
      },
      {
        "lineNumber": 76,
        "author": {
          "gitId": "silvernitro"
        },
        "content": "                                                       \"be removed.\");"
      },
      {
        "lineNumber": 77,
        "author": {
          "gitId": "silvernitro"
        },
        "content": "        }"
      },
      {
        "lineNumber": 78,
        "author": {
          "gitId": "silvernitro"
        },
        "content": "        Task removed \u003d itemList.remove(itemIndex - 1);"
      },
      {
        "lineNumber": 79,
        "author": {
          "gitId": "silvernitro"
        },
        "content": "        System.out.println(\"This task has been removed: \" + removed);"
      },
      {
        "lineNumber": 80,
        "author": {
          "gitId": "silvernitro"
        },
        "content": "    }"
      },
      {
        "lineNumber": 81,
        "author": {
          "gitId": "silvernitro"
        },
        "content": ""
      },
      {
        "lineNumber": 82,
        "author": {
          "gitId": "silvernitro"
        },
        "content": "    void printList() {"
      },
      {
        "lineNumber": 83,
        "author": {
          "gitId": "silvernitro"
        },
        "content": "        for (int i \u003d 1; i \u003c\u003d itemList.size(); i++) {"
      },
      {
        "lineNumber": 84,
        "author": {
          "gitId": "silvernitro"
        },
        "content": "            System.out.println(i + \". \" + itemList.get(i - 1));"
      },
      {
        "lineNumber": 85,
        "author": {
          "gitId": "silvernitro"
        },
        "content": "        }"
      },
      {
        "lineNumber": 86,
        "author": {
          "gitId": "silvernitro"
        },
        "content": "    }"
      },
      {
        "lineNumber": 87,
        "author": {
          "gitId": "silvernitro"
        },
        "content": "}"
      }
    ],
    "authorContributionMap": {
      "silvernitro": 87
    }
  },
  {
    "path": "src/main/java/Todo.java",
    "fileType": "java",
    "lines": [
      {
        "lineNumber": 1,
        "author": {
          "gitId": "silvernitro"
        },
        "content": "public class Todo extends Task {"
      },
      {
        "lineNumber": 2,
        "author": {
          "gitId": "silvernitro"
        },
        "content": "    public Todo(String description) {"
      },
      {
        "lineNumber": 3,
        "author": {
          "gitId": "silvernitro"
        },
        "content": "        super(description);"
      },
      {
        "lineNumber": 4,
        "author": {
          "gitId": "silvernitro"
        },
        "content": "    }"
      },
      {
        "lineNumber": 5,
        "author": {
          "gitId": "silvernitro"
        },
        "content": ""
      },
      {
        "lineNumber": 6,
        "author": {
          "gitId": "silvernitro"
        },
        "content": "    @Override"
      },
      {
        "lineNumber": 7,
        "author": {
          "gitId": "silvernitro"
        },
        "content": "    public String toString() {"
      },
      {
        "lineNumber": 8,
        "author": {
          "gitId": "silvernitro"
        },
        "content": "        return \"[T] \" + super.toString();"
      },
      {
        "lineNumber": 9,
        "author": {
          "gitId": "silvernitro"
        },
        "content": "    }"
      },
      {
        "lineNumber": 10,
        "author": {
          "gitId": "silvernitro"
        },
        "content": "}"
      }
    ],
    "authorContributionMap": {
      "silvernitro": 10
    }
  },
  {
    "path": "text-ui-test/input.txt",
    "fileType": "txt",
    "lines": [
      {
        "lineNumber": 1,
        "author": {
          "gitId": "silvernitro"
        },
        "content": "todo borrow book"
      },
      {
        "lineNumber": 2,
        "author": {
          "gitId": "silvernitro"
        },
        "content": "deadline return book /by sunday"
      },
      {
        "lineNumber": 3,
        "author": {
          "gitId": "silvernitro"
        },
        "content": "event meet friend /at wed 2pm"
      },
      {
        "lineNumber": 4,
        "author": {
          "gitId": "silvernitro"
        },
        "content": "list"
      },
      {
        "lineNumber": 5,
        "author": {
          "gitId": "silvernitro"
        },
        "content": "done 1"
      },
      {
        "lineNumber": 6,
        "author": {
          "gitId": "silvernitro"
        },
        "content": "list"
      },
      {
        "lineNumber": 7,
        "author": {
          "gitId": "silvernitro"
        },
        "content": "done 2"
      },
      {
        "lineNumber": 8,
        "author": {
          "gitId": "silvernitro"
        },
        "content": "list"
      },
      {
        "lineNumber": 9,
        "author": {
          "gitId": "silvernitro"
        },
        "content": "done 3"
      },
      {
        "lineNumber": 10,
        "author": {
          "gitId": "silvernitro"
        },
        "content": "list"
      },
      {
        "lineNumber": 11,
        "author": {
          "gitId": "silvernitro"
        },
        "content": "delete 1"
      },
      {
        "lineNumber": 12,
        "author": {
          "gitId": "silvernitro"
        },
        "content": "list"
      },
      {
        "lineNumber": 13,
        "author": {
          "gitId": "silvernitro"
        },
        "content": "delete 1"
      },
      {
        "lineNumber": 14,
        "author": {
          "gitId": "silvernitro"
        },
        "content": "list"
      },
      {
        "lineNumber": 15,
        "author": {
          "gitId": "silvernitro"
        },
        "content": "delete 2"
      },
      {
        "lineNumber": 16,
        "author": {
          "gitId": "silvernitro"
        },
        "content": "list"
      },
      {
        "lineNumber": 17,
        "author": {
          "gitId": "silvernitro"
        },
        "content": "hello world"
      },
      {
        "lineNumber": 18,
        "author": {
          "gitId": "silvernitro"
        },
        "content": "todo"
      },
      {
        "lineNumber": 19,
        "author": {
          "gitId": "silvernitro"
        },
        "content": "done 5"
      },
      {
        "lineNumber": 20,
        "author": {
          "gitId": "silvernitro"
        },
        "content": "bye"
      }
    ],
    "authorContributionMap": {
      "silvernitro": 20
    }
  },
  {
    "path": "text-ui-test/runtest.sh",
    "fileType": "sh",
    "lines": [
      {
        "lineNumber": 1,
        "author": {
          "gitId": "-"
        },
        "content": "#!/usr/bin/env bash"
      },
      {
        "lineNumber": 2,
        "author": {
          "gitId": "-"
        },
        "content": ""
      },
      {
        "lineNumber": 3,
        "author": {
          "gitId": "-"
        },
        "content": "# create bin directory if it doesn\u0027t exist"
      },
      {
        "lineNumber": 4,
        "author": {
          "gitId": "-"
        },
        "content": "if [ ! -d \"../bin\" ]"
      },
      {
        "lineNumber": 5,
        "author": {
          "gitId": "-"
        },
        "content": "then"
      },
      {
        "lineNumber": 6,
        "author": {
          "gitId": "-"
        },
        "content": "    mkdir ../bin"
      },
      {
        "lineNumber": 7,
        "author": {
          "gitId": "-"
        },
        "content": "fi"
      },
      {
        "lineNumber": 8,
        "author": {
          "gitId": "-"
        },
        "content": ""
      },
      {
        "lineNumber": 9,
        "author": {
          "gitId": "-"
        },
        "content": "# delete output from previous run"
      },
      {
        "lineNumber": 10,
        "author": {
          "gitId": "-"
        },
        "content": "if [ -e \"./ACTUAL.TXT\" ]"
      },
      {
        "lineNumber": 11,
        "author": {
          "gitId": "-"
        },
        "content": "then"
      },
      {
        "lineNumber": 12,
        "author": {
          "gitId": "-"
        },
        "content": "    rm ACTUAL.TXT"
      },
      {
        "lineNumber": 13,
        "author": {
          "gitId": "-"
        },
        "content": "fi"
      },
      {
        "lineNumber": 14,
        "author": {
          "gitId": "-"
        },
        "content": ""
      },
      {
        "lineNumber": 15,
        "author": {
          "gitId": "-"
        },
        "content": "# compile the code into the bin folder, terminates if error occurred"
      },
      {
        "lineNumber": 16,
        "author": {
          "gitId": "silvernitro"
        },
        "content": "if ! javac -cp ../src -Xlint:none -d ../bin ../src/main/java/*.java"
      },
      {
        "lineNumber": 17,
        "author": {
          "gitId": "-"
        },
        "content": "then"
      },
      {
        "lineNumber": 18,
        "author": {
          "gitId": "-"
        },
        "content": "    echo \"********** BUILD FAILURE **********\""
      },
      {
        "lineNumber": 19,
        "author": {
          "gitId": "-"
        },
        "content": "    exit 1"
      },
      {
        "lineNumber": 20,
        "author": {
          "gitId": "-"
        },
        "content": "fi"
      },
      {
        "lineNumber": 21,
        "author": {
          "gitId": "-"
        },
        "content": ""
      },
      {
        "lineNumber": 22,
        "author": {
          "gitId": "-"
        },
        "content": "# run the program, feed commands from input.txt file and redirect the output to the ACTUAL.TXT"
      },
      {
        "lineNumber": 23,
        "author": {
          "gitId": "-"
        },
        "content": "java -classpath ../bin Duke \u003c input.txt \u003e ACTUAL.TXT"
      },
      {
        "lineNumber": 24,
        "author": {
          "gitId": "-"
        },
        "content": ""
      },
      {
        "lineNumber": 25,
        "author": {
          "gitId": "silvernitro"
        },
        "content": "## convert to UNIX format"
      },
      {
        "lineNumber": 26,
        "author": {
          "gitId": "silvernitro"
        },
        "content": "#cp EXPECTED.TXT EXPECTED-UNIX.TXT"
      },
      {
        "lineNumber": 27,
        "author": {
          "gitId": "silvernitro"
        },
        "content": "#dos2unix ACTUAL.TXT EXPECTED-UNIX.TXT"
      },
      {
        "lineNumber": 28,
        "author": {
          "gitId": "-"
        },
        "content": ""
      },
      {
        "lineNumber": 29,
        "author": {
          "gitId": "-"
        },
        "content": "# compare the output to the expected output"
      },
      {
        "lineNumber": 30,
        "author": {
          "gitId": "silvernitro"
        },
        "content": "diff ACTUAL.TXT EXPECTED.TXT"
      },
      {
        "lineNumber": 31,
        "author": {
          "gitId": "-"
        },
        "content": "if [ $? -eq 0 ]"
      },
      {
        "lineNumber": 32,
        "author": {
          "gitId": "-"
        },
        "content": "then"
      },
      {
        "lineNumber": 33,
        "author": {
          "gitId": "-"
        },
        "content": "    echo \"Test result: PASSED\""
      },
      {
        "lineNumber": 34,
        "author": {
          "gitId": "-"
        },
        "content": "    exit 0"
      },
      {
        "lineNumber": 35,
        "author": {
          "gitId": "-"
        },
        "content": "else"
      },
      {
        "lineNumber": 36,
        "author": {
          "gitId": "-"
        },
        "content": "    echo \"Test result: FAILED\""
      },
      {
        "lineNumber": 37,
        "author": {
          "gitId": "-"
        },
        "content": "    exit 1"
      },
      {
        "lineNumber": 38,
        "author": {
          "gitId": "-"
        },
        "content": "fi"
      }
    ],
    "authorContributionMap": {
      "silvernitro": 5,
      "-": 33
    }
  }
]
