{
  "authorDailyContributionsMap": {
    "zhaojj2209": [
      {
        "date": "2020-08-16",
        "commitResults": [
          {
            "hash": "6721cd825cf226cbfdccef5f2085fec1d7c06123",
            "messageTitle": "implemented level 1",
            "messageBody": "",
            "tags": [
              "Level-1"
            ],
            "fileTypesAndContributionMap": {
              "java": {
                "insertions": 18,
                "deletions": 6
              }
            }
          }
        ]
      },
      {
        "date": "2020-08-18",
        "commitResults": [
          {
            "hash": "ec74234776e4b02dbf9cba7d133b506bc3ccbc22",
            "messageTitle": "implemented level 2",
            "messageBody": "",
            "tags": [
              "Level-2",
              "A-Collections"
            ],
            "fileTypesAndContributionMap": {
              "java": {
                "insertions": 10,
                "deletions": 2
              }
            }
          },
          {
            "hash": "4b00df6a665b37da6f7451fdde2fdc517cee8b4e",
            "messageTitle": "created task class",
            "messageBody": "",
            "tags": [
              "A-Classes"
            ],
            "fileTypesAndContributionMap": {
              "java": {
                "insertions": 22,
                "deletions": 0
              }
            }
          },
          {
            "hash": "72f9601f6193d4a9fc06eeeb5029a7e1b1a9306c",
            "messageTitle": "implemented level 3",
            "messageBody": "",
            "tags": [
              "Level-3"
            ],
            "fileTypesAndContributionMap": {
              "java": {
                "insertions": 13,
                "deletions": 3
              }
            }
          },
          {
            "hash": "2abd8ec8f39bfdefbb992ae01b9f6d755016261d",
            "messageTitle": "added inheritance classes",
            "messageBody": "",
            "tags": [
              "A-Inheritance"
            ],
            "fileTypesAndContributionMap": {
              "java": {
                "insertions": 34,
                "deletions": 0
              }
            }
          },
          {
            "hash": "8ce898283f4c590dea82b560f7abea139400c2e8",
            "messageTitle": "implemented level 4",
            "messageBody": "",
            "tags": [
              "Level-4"
            ],
            "fileTypesAndContributionMap": {
              "java": {
                "insertions": 17,
                "deletions": 11
              }
            }
          },
          {
            "hash": "e69683c46846cdbc5a152cebe3cb42a7b0aeafe5",
            "messageTitle": "I/O redirection testing",
            "messageBody": "",
            "tags": [
              "A-TextUiTesting"
            ],
            "fileTypesAndContributionMap": {
              "txt": {
                "insertions": 7,
                "deletions": 0
              },
              "sh": {
                "insertions": 14,
                "deletions": 18
              }
            }
          },
          {
            "hash": "56859fd7445e47675c31804368c534572fa37e94",
            "messageTitle": "added exception",
            "messageBody": "",
            "tags": [
              "A-Exceptions"
            ],
            "fileTypesAndContributionMap": {
              "java": {
                "insertions": 5,
                "deletions": 0
              }
            }
          },
          {
            "hash": "ec3fa2362cfa3ffbb0b878e2b01199a9e51f1104",
            "messageTitle": "implemented level 5",
            "messageBody": "",
            "tags": [
              "Level-5"
            ],
            "fileTypesAndContributionMap": {
              "java": {
                "insertions": 48,
                "deletions": 27
              },
              "sh": {
                "insertions": 1,
                "deletions": 1
              }
            }
          },
          {
            "hash": "ba3692cc8106ad875525f29620880c28b1072c42",
            "messageTitle": "implemented level 6",
            "messageBody": "",
            "tags": [
              "Level-6"
            ],
            "fileTypesAndContributionMap": {
              "txt": {
                "insertions": 3,
                "deletions": 0
              },
              "java": {
                "insertions": 26,
                "deletions": 10
              }
            }
          }
        ]
      },
      {
        "date": "2020-08-20",
        "commitResults": [
          {
            "hash": "ddedc1059e9204e5d35661214b6b89c3b0e8baea",
            "messageTitle": "used enums",
            "messageBody": "",
            "tags": [
              "A-Enums"
            ],
            "fileTypesAndContributionMap": {
              "java": {
                "insertions": 85,
                "deletions": 44
              }
            }
          }
        ]
      },
      {
        "date": "2020-08-22",
        "commitResults": [
          {
            "hash": "62f18c440c6e289f458fb78ad42baf9d8b3a243c",
            "messageTitle": "fix switch indentation",
            "messageBody": "",
            "fileTypesAndContributionMap": {
              "java": {
                "insertions": 67,
                "deletions": 67
              }
            }
          },
          {
            "hash": "0b824d2225a4fba45e07794a7c51cb5abe23e75c",
            "messageTitle": "Implement level 7",
            "messageBody": "",
            "fileTypesAndContributionMap": {
              "java": {
                "insertions": 79,
                "deletions": 26
              }
            }
          }
        ]
      },
      {
        "date": "2020-08-23",
        "commitResults": [
          {
            "hash": "3d99c238320d79aaec7ce6743fad6b3a739aba1a",
            "messageTitle": "Implement level 8",
            "messageBody": "",
            "fileTypesAndContributionMap": {
              "txt": {
                "insertions": 2,
                "deletions": 2
              },
              "java": {
                "insertions": 18,
                "deletions": 8
              }
            }
          }
        ]
      }
    ]
  },
  "authorFileTypeContributionMap": {
    "zhaojj2209": {
      "java": 243,
      "md": 0,
      "fxml": 0,
      "sh": 4,
      "bat": 0,
      "gradle": 0,
      "txt": 10
    }
  },
  "authorContributionVariance": {
    "zhaojj2209": 10105.841
  },
  "authorDisplayNameMap": {
    "zhaojj2209": "ZHAO..JING"
  }
}
